sc_compression/__init__.py
sc_compression/__main__.py
sc_compression/compressor.py
sc_compression/decompressor.py
sc_compression/signatures.py
sc_compression/exceptions/__init__.py
sc_compression/exceptions/unknown_file_magic.py
sc_compression/support/__init__.py
sc_compression/support/lzham.exe
sc_compression/support/lzham.py
sc_compression/utils/__init__.py
sc_compression/utils/common.py
sc_compression/utils/reader.py
sc_compression/utils/writer.py
sc_compression-0.6.6.dist-info/LICENSE
sc_compression-0.6.6.dist-info/METADATA
sc_compression-0.6.6.dist-info/WHEEL
sc_compression-0.6.6.dist-info/entry_points.txt
sc_compression-0.6.6.dist-info/top_level.txt
sc_compression-0.6.6.dist-info/RECORD
