Metadata-Version: 2.1
Name: sc-compression
Version: 0.6.6
Summary: SC Compression
Home-page: https://github.com/xcoder-tool/sc-compression
Author: Vorono4ka
Author-email: crowo4ka@gmail.com
License: GPLv3
Classifier: Programming Language :: Python :: 3
Classifier: License :: OSI Approved :: GNU General Public License v3 (GPLv3)
Classifier: Operating System :: OS Independent
Requires-Python: >=3.5
License-File: LICENSE
Requires-Dist: zstandard
